Metadata-Version: 1.0
Name: joker-test
Version: 0.0.2
Summary: 吃枣药丸
Home-page: http://www.baidu.com
Author: joker
Author-email: joker.code@qq.com
License: UNKNOWN
Platform: UNKNOWN
